{
    "languageserver": {
        "intelephense": {
            "command": "intelephense",
            "args": ["--stdio"],
            "filetypes": ["php"],
            "initializationOptions": {
                "storagePath": "/tmp/intelephense"
            }
        },
        "golang": {
            "command": "go-langserver",
            "filetypes": ["go"],
            "initializationOptions": {
                "gocodeCompletionEnabled": true,
                "diagnosticsEnabled": true,
                "lintTool": "golint"
            }
        }
    }
}
